clickatell/__init__.py
clickatell/controller.py
clickatell/http/__init__.py
clickatell/rest/__init__.py
clickatell_platform-2.0.1.dist-info/LICENSE.md
clickatell_platform-2.0.1.dist-info/METADATA
clickatell_platform-2.0.1.dist-info/WHEEL
clickatell_platform-2.0.1.dist-info/top_level.txt
clickatell_platform-2.0.1.dist-info/RECORD
