Metadata-Version: 2.1
Name: clickatell-platform
Version: 2.0.1
Summary: Library for interacting with the Clickatell Platform SMS Gateway
Home-page: https://github.com/clickatell/clickatell-python
Author: Chris Brand, Stephen Leibbrandt, Renier Minne
Author-email: support@clickatell.com
License: LICENSE
Keywords: clickatell,sms,platform
Platform: UNKNOWN
Classifier: Programming Language :: Python
Classifier: License :: OSI Approved :: MIT License
Classifier: Operating System :: OS Independent
Requires-Dist: httplib2
